slack_ui/__init__.py
slack_ui/blocks.py
slack_ui/domain.py
slack_ui/forms.py
slack_ui/utils.py
slack_ui/views.py
slack_ui-0.1.1.dist-info/METADATA
slack_ui-0.1.1.dist-info/WHEEL
slack_ui-0.1.1.dist-info/RECORD
