Metadata-Version: 2.1
Name: slack_ui
Version: 0.1.1
Summary: Python's Slack Blocks Builder aims to provide an easy-to-use interface for creating complex Slack messages using Blocks, improving on Slack Bolt's native functionality.
Author: Mikołaj Jeziorny
Author-email: mikijezi@gmail.com
Requires-Python: >=3.10,<4.0
Classifier: Programming Language :: Python :: 3
Classifier: Programming Language :: Python :: 3.10
Classifier: Programming Language :: Python :: 3.11
